Metadata-Version: 2.1
Name: better_random
Version: 0.1
Summary: A library with a hidden secret
Author: Johannes Schießl
Author-email: contact.johannes@icloud.com
